{
"114-gravel-race": "2026-03-28",
"3-state-3-mountain-challenge": "2025-05-06",
"3rides-aachen": "2026-07-19",
"3rides-gran-fondo": "2026-04-25",
"5-mila-marche-gran-fondo": "2026-09-20",
"6-hours-of-syllamo": "2026-03-20",
"66-degres-sud": "2026-04-18",
"66-south-pyrenees": "2026-09-26",
"947-ride-joburg": "2025-10-26",
"adac-velotour": "2026-05-01",
"adelaide-epic-ride": "2026-01-23",
"aitana-tour": "2026-05-31",
"albia-holy-cow": "2026-07-18",
"alentejo-gravel": "2026-10-25",
"algarve-gran-fondo": "2026-02-21",
"almanzo-100": "2026-05-16",
"alpe-dhuzes": "2026-06-04",
"alpen-challenge-lenzerheide": "2026-06-21",
"alpenbrevet": "2026-09-05",
"americas-most-beautiful-bike-ride": "2026-06-07",
"amstel-gold-race-toerversie": "2026-04-18",
"amys-gran-fondo": "2026-09-06",
"ardenne-gravel-stages": "2026-09-25",
"arlberg-giro": "2026-08-02",
"around-the-bay-in-a-day": "2026-10-18",
"assault-on-mt-mitchell": "2026-05-18",
"atlas-gran-fondo": "2026-11-21",
"atlas-mountain-race": "2026-02-06",
"back-forty-highlander": "2026-09-05",
"badlands": "2026-08-30",
"balatonfondo": "2026-05-01",
"bald-eagle-gravel-grinder": "2026-04-12",
"balkan-gravel": "2026-05-29",
"barry-roubaix": "2027-04-17",
"battenkill": "2026-05-09",
"bealach-mor": "2026-05-16",
"bear-100": "2026-04-02",
"bear-howard-gravel": "2026-08-01",
"beaver-dam-gravel-grinder": "2026-06-20",
"bend-dirt-fest": "2026-07-11",
"bergen-voss": "2026-06-06",
"berryman-epic": "2025-10-18",
"best-buddies-challenge-hyannis-port": "2026-05-30",
"big-sky-gravel": "2026-08-30",
"big-sugar": "2026-10-17",
"bighorn-gravel": "2026-06-20",
"bike-abu-dhabi-gran-fondo": "2025-12-21",
"bike-ms-nyc": "2026-10-18",
"bikingman-corsica": "2026-05-24",
"birkebeinerrittet-road": "2026-08-29",
"black-forest-gravel": "2026-07-25",
"bluewater-gran-fondo": "2026-08-02",
"bohemian-border-bash": "2025-09-06",
"boone-gran-fondo": "2026-08-02",
"bordeaux-paris-ultra-cycling": "2026-05-22",
"boulder-roubaix": "2026-04-26",
"bowral-classic": "2026-10-18",
"bp-ms-150-texas": "2026-04-25",
"bra-bra-fenix-internazionale": "2026-05-17",
"burgr-95": "2025-07-12",
"burnt-bridge-classic": "2026-06-14",
"bwr-arizona": "2027-03-07",
"bwr-california": "2027-04-25",
"bwr-cedar-city": "2026-06-13",
"bwr-montana": "2026-06-19",
"bwr-san-diego": "2026-05-02",
"bwr-utah": "2026-06-12",
"cadel-evans-great-ocean-road-ride": "2026-01-31",
"camp-michaux-gravel-grinder": "2026-06-28",
"canmore-crux": "2026-06-07",
"cape-town-cycle-tour": "2026-03-08",
"carpathian-gravel": "2026-07-04",
"castellon-gravel-race": "2026-02-22",
"cedar-blitz": "2026-07-12",
"chase-the-sun-norway": "2026-06-20",
"chasing-cancellara": "2026-06-27",
"cheaha-challenge": "2026-05-16",
"cheaha-challenge-gran-fondo": "2026-05-16",
"chequamegon-mtb": "2026-09-20",
"chiang-mai-gran-fondo": "2026-03-22",
"chino-grinder": "2026-10-17",
"cicloturista-cerdanya": "2026-07-04",
"cinturon-ciclista-mallorca": "2026-02-08",
"cirrem": "2026-02-28",
"clare-classic": "2026-02-15",
"clarkes-gambit": "2026-08-21",
"coast-to-coast": "2026-06-27",
"cohutta-gravel-grinder": "2026-04-18",
"colnago-cycling-festival": "2026-06-07",
"colorado-trail-race": "2026-08-02",
"copper-triangle": "2026-08-01",
"cow-pie-classic": "2026-06-08",
"cowboy-crusher": "2026-07-11",
"cowichan-crusher-gravel-fondo": "2026-05-31",
"crc-506-gran-fondo-costa-rica": "2026-06-07",
"crooked-gravel": "2026-08-01",
"crusher-in-the-tushar": "2026-07-11",
"crystal-bear": "2026-05-17",
"cyclassics-hamburg": "2026-08-16",
"cycle-oregon": "2026-08-28",
"cycling-shimanami": "2026-10-25",
"cyclotour-du-leman": "2026-10-18",
"cykelvasan": "2026-08-07",
"cyprus-gran-fondo": "2026-04-03",
"d2r2": "2026-08-22",
"dalby-grit": "2026-06-19",
"dartmoor-classic": "2026-06-21",
"dartmoor-legend-ultra": "2026-07-11",
"de-ronde-van-grampian": "2026-08-01",
"dead-swede-gravel": "2027-06-05",
"death-ride": "2026-07-11",
"devils-cardigan": "2027-06-19",
"dirty-30": "2026-04-19",
"dirty-dino": "2026-06-28",
"dirty-hector": "2026-05-24",
"dirty-pecan": "2026-03-07",
"dirty-reiver": "2026-04-24",
"dirty-sheets-gravel-grind": "2026-02-08",
"dolomitenradrundfahrt": "2026-06-14",
"douro-gran-fondo": "2026-05-10",
"dragon-ride": "2026-06-14",
"dreilander-giro": "2026-06-28",
"dunoon-dirt-dash": "2026-09-27",
"dusty-bandita": "2026-06-06",
"dusty-gravel-lacs-de-leau-dheure": "2025-04-19",
"dusty-gravel-series-andenne": "2026-04-12",
"edition-zero": "2026-11-28",
"eislek-gravel": "2027-06-20",
"el-tour-de-tucson": "2026-11-21",
"engadin-radmarathon": "2026-07-03",
"epic-gran-canaria": "2026-02-07",
"eroica-cuba": "2026-02-14",
"eroica-dolomiti": "2026-09-05",
"eroica-germania": "2026-08-22",
"eroica-hispania": "2026-06-06",
"eroica-japan": "2026-04-11",
"eroica-south-africa": "2026-04-10",
"essential-gravel": "2026-06-14",
"etape-caledonia": "2026-05-17",
"etape-du-dales": "2025-06-08",
"etape-loch-ness": "2026-04-26",
"fairfield-harvest-rush": "2026-10-03",
"farmers-daughter": "2026-05-13",
"fast-fitty": "2026-08-15",
"filthy-50": "2026-10-10",
"final-frontier-patagonia": "2026-03-08",
"five-boro-bike-tour": "2026-05-03",
"flanders-legacy-gravel": "2026-10-18",
"flandrien-ride": "2026-04-04",
"flint-hills-death-ride": "2026-04-04",
"fools-gold-gravel-grinder": "2026-09-12",
"forbidden-gravel": "2026-09-20",
"fred-whitton-challenge": "2026-05-10",
"fuego-mtb": "2026-04-18",
"fyn-rundt": "2026-05-03",
"galactic-grinder": "2025-04-19",
"galibier-challenge": "2026-06-07",
"garmin-gravel-worlds": "2026-08-19",
"gent-wevelgem-cyclo": "2026-03-28",
"gf-gavia-e-mortirolo": "2026-06-28",
"gf-samoens-ultra-raid": "2026-06-05",
"gfny-aguascalientes": "2026-03-22",
"gfny-bahamas": "2025-11-09",
"gfny-bali": "2026-02-15",
"gfny-bremen": "2026-08-30",
"gfny-cannes": "2026-04-12",
"gfny-chile": "2026-09-27",
"gfny-cozumel": "2026-11-08",
"gfny-dominican-republic": "2026-03-15",
"gfny-kuala-lumpur": "2026-05-12",
"gfny-la-vaujany-alpe-dhuez": "2026-06-21",
"gfny-lourdes-tourmalet": "2026-06-14",
"gfny-maryland-cambridge": "2026-10-04",
"gfny-miami": "2026-11-08",
"gfny-new-york": "2026-05-17",
"gfny-nyc": "2026-05-17",
"gfny-paracas": "2026-06-07",
"gfny-philippines": "2026-03-15",
"gfny-pittsburgh": "2026-09-20",
"gfny-punta-del-este": "2026-03-15",
"gfny-salinas": "2026-03-01",
"gfny-san-juan": "2026-03-01",
"gfny-toscana": "2026-04-06",
"gfny-uppsala": "2026-08-23",
"gfny-zapopan": "2026-05-03",
"ghost-of-the-gravel": "2026-06-14",
"giro-delle-dolomiti": "2026-07-13",
"giro-ride-like-a-pro-usa": "2026-02-21",
"giro-sardegna-gravel": "2026-04-30",
"glengarry-games-gravel-run": "2026-08-02",
"glenwood-gravel": "2026-08-10",
"goteborgsgirot": "2026-05-24",
"grafton-to-inverell-classic": "2026-03-14",
"gran-fondo-argentina": "2025-10-12",
"gran-fondo-asheville": "2026-07-19",
"gran-fondo-badlands": "2026-07-04",
"gran-fondo-baskent": "2026-08-23",
"gran-fondo-collado-del-condor": "2026-03-22",
"gran-fondo-curacavi": "2026-04-19",
"gran-fondo-eilat": "2026-12-11",
"gran-fondo-firenze": "2024-04-14",
"gran-fondo-florida": "2026-03-22",
"gran-fondo-gdynia": "2026-06-21",
"gran-fondo-hainan": "2025-12-12",
"gran-fondo-hangzhou": "2026-05-23",
"gran-fondo-hincapie": "2026-10-17",
"gran-fondo-il-lombardia": "2026-10-11",
"gran-fondo-jasper": "2026-06-06",
"gran-fondo-jordan": "2026-01-30",
"gran-fondo-la-fausto-coppi": "2026-06-28",
"gran-fondo-loutraki": "2026-11-15",
"gran-fondo-marco-pantani": "2025-09-13",
"gran-fondo-maryland": "2026-09-20",
"gran-fondo-mont-tremblant": "2026-08-21",
"gran-fondo-mont-ventoux": "2026-06-07",
"gran-fondo-nirvana-antalya": "2025-11-07",
"gran-fondo-ozarks": "2026-03-12",
"gran-fondo-panama": "2026-03-08",
"gran-fondo-pirineus": "2026-06-28",
"gran-fondo-san-diego": "2026-04-19",
"gran-fondo-suisse": "2026-07-10",
"gran-fondo-utah": "2026-06-13",
"granfondo-alberto-contador": "2026-09-19",
"granfondo-alpi-del-mare": "2026-09-20",
"granfondo-belgium": "2026-03-29",
"granfondo-bogota": "2025-12-07",
"granfondo-bulgaria": "2026-06-21",
"granfondo-charlevoix": "2026-05-31",
"granfondo-colnago": "2026-04-10",
"granfondo-felice-gimondi": "2026-05-10",
"granfondo-gf-do-porto": "2026-04-26",
"granfondo-gottardo": "2026-08-23",
"granfondo-la-guadeloupe": "2025-12-07",
"granfondo-laigueglia": "2026-02-22",
"granfondo-leiria": "2026-03-29",
"granfondo-livigno-ale": "2026-06-27",
"granfondo-matildica": "2026-09-13",
"granfondo-moser": "2026-06-05",
"granfondo-nove-colli": "2026-05-24",
"granfondo-novi-sad": "2026-06-07",
"granfondo-pinarello": "2026-07-12",
"granfondo-pomerode": "2026-11-08",
"granfondo-riviera-nayarit": "2026-04-18",
"granfondo-san-sebastian": "2026-07-11",
"granfondo-serra-da-estrela": "2026-06-28",
"granfondo-tre-valli-varesine": "2026-10-03",
"granfondo-via-del-sale": "2026-03-29",
"grasshopper-series": "2026-01-25",
"grasslands-100": "2026-03-21",
"grassroots-gravel": "2026-10-09",
"gravel-and-granite": "2026-05-15",
"gravel-and-tar-classic": "2027-01-16",
"gravel-battle-of-sumter-forest": "2027-03-13",
"gravel-brazil": "2026-03-08",
"gravel-del-fuego": "2026-04-11",
"gravel-des-flandres": "2025-09-14",
"gravel-fever": "2025-09-26",
"gravel-grit-n-grind": "2026-09-26",
"gravel-locos": "2027-05-22",
"gravel-one-fifty": "2026-04-25",
"gravel-revival": "2026-10-16",
"gravel-rocks": "2026-07-10",
"gravel-roll-pecan-shaker": "2026-10-17",
"gravel-roubaix": "2026-04-26",
"gravel-suisse": "2026-07-12",
"gravel-unravel-bon-jon-pass-out": "2026-06-13",
"gravel-unravel-why-not-chee": "2026-07-18",
"gravel-worlds": "2026-08-19",
"gravel-worlds-amateur": "2026-08-19",
"gravelista": "2026-10-25",
"gray-duck-grit": "2026-09-05",
"great-otway-gravel-grind": "2026-02-28",
"greek-gravel": "2026-05-23",
"grinduro-california": "2026-09-12",
"grinduro-italy": "2026-09-26",
"grusk": "2025-12-01",
"gruyere-cycling-tour": "2026-07-12",
"gun-flint-44": "2025-09-27",
"gunni-grinder": "2026-09-12",
"haervejslobet": "2026-06-27",
"haldon-heroic": "2026-04-12",
"haleakala-cycle-to-the-sun": "2025-08-02",
"halvvattern": "2026-06-06",
"hardwood-hustle": "2025-09-27",
"hart-hills": "2026-05-09",
"haute-route-alps": "2026-08-23",
"haute-route-gravel": "2026-08-29",
"heathland-gravel": "2026-08-09",
"heck-of-the-north": "2026-09-26",
"hegau-gravel-race": "2026-07-05",
"hell-of-hunterdon": "2026-03-29",
"hellhole-gravel-grind": "2026-10-02",
"helsinki-gran-fondo": "2026-08-30",
"heywood-ride": "2026-05-16",
"hibernator": "2025-10-04",
"highlands-gran-fondo": "2026-06-07",
"highlands-gravel-classic": "2027-04-24",
"holly-shelter-gravel-grinder": "2026-03-28",
"homegrown-gravel-adventure": "2026-02-28",
"hot-springs-gravel-gauntlet": "2027-05-15",
"hottern-hell-hundred": "2026-08-29",
"houffa-gravel": "2026-08-30",
"hungry-bear-100": "2027-05-08",
"iceman-cometh": "2026-11-07",
"inthanon-challenge": "2026-02-08",
"iowa-state-gravel-tt-championship": "2026-09-06",
"iowa-wind-and-rock": "2026-04-19",
"iron-cross": "2025-10-19",
"iron-horse-bicycle-classic": "2026-05-24",
"istria-granfondo": "2026-04-11",
"jamtlandspilen": "2026-08-15",
"jedermann-rennen-koln": "2026-05-17",
"jeroboam": "2026-07-18",
"just-gravel": "2026-10-03",
"kal-tour-dirty-100": "2026-02-20",
"kalona-horseshoe": "2026-05-09",
"karukinka": "2026-02-25",
"kettle-mettle": "2027-06-19",
"king-of-the-lake": "2026-09-26",
"king-price-race-to-sun": "2026-05-16",
"knysna-cycle-tour": "2026-07-12",
"kowtown-gravel": "2026-06-13",
"krk-gran-fondo": "2026-04-25",
"la-marmotte": "2026-06-28",
"la-ruta-de-los-conquistadores": "2026-10-29",
"la-stelvio-santini": "2026-06-07",
"la-vaujany": "2025-06-15",
"lake-country-gravel": "2026-07-25",
"lake-taupo-cycle-challenge": "2026-11-28",
"lardechoise": "2026-06-10",
"lariegeoise-cyclosportive": "2026-06-27",
"lauf-gritfest": "2026-06-19",
"lauf-true-grit": "2027-03-18",
"le-grand-du-nord": "2027-05-22",
"le-loop": "2026-06-27",
"le-race": "2026-03-21",
"leadville-100": "2026-08-15",
"leroica": "2026-10-04",
"les-trois-ballons": "2026-06-07",
"letape-argentina": "2026-03-22",
"letape-brazil": "2026-09-27",
"letape-bulgaria": "2026-07-05",
"letape-cancun": "2026-05-17",
"letape-costa-rica": "2026-08-09",
"letape-czech-republic": "2026-06-20",
"letape-denmark": "2026-06-27",
"letape-du-tour": "2026-07-19",
"letape-du-tour-femmes": "2026-08-06",
"letape-dubai": "2026-01-25",
"letape-greece": "2026-04-04",
"letape-italy-piemonte": "2026-05-31",
"letape-mexico-city": "2026-11-30",
"letape-norway": "2026-06-20",
"letape-poland": "2026-09-29",
"letape-portugal": "2025-09-28",
"letape-romania": "2026-08-16",
"letape-slovakia": "2026-08-23",
"letape-slovenia": "2025-09-07",
"letape-taiwan": "2026-04-12",
"letape-thailand": "2025-05-15",
"letape-turkey": "2026-09-19",
"levis-granfondo": "2026-10-03",
"liege-bastogne-liege-challenge": "2026-04-25",
"little-apple-100": "2027-08-08",
"little-sugar-mtb": "2026-10-11",
"london-to-brighton": "2026-06-21",
"lone-wolf-gravel": "2026-09-27",
"lost-and-found-gravel": "2027-06-12",
"lost-river-classic": "2026-08-16",
"lotoja-classic": "2026-09-12",
"lowell-classic": "2026-10-24",
"maap-beechworth-granite-classic": "2026-04-17",
"mad-gravel": "2026-09-05",
"mallorca-312": "2026-04-25",
"mammoth-tuff": "2026-09-19",
"maraton-franja": "2026-06-12",
"maratona-dles-dolomites": "2026-07-05",
"marji-gesick": "2026-09-18",
"marly-grav": "2026-05-10",
"marmotte-granfondo-sestriere": "2026-07-05",
"marmotte-pyrenees": "2025-08-24",
"marys-mayhem": "2026-10-16",
"melting-mann": "2026-03-28",
"mid-south": "2026-03-13",
"mid-state-gravel-grinder": "2026-08-15",
"midnight-sun-randonnee": "2026-06-14",
"migration-gravel-race": "2026-06-10",
"milano-sanremo-gran-fondo": "2026-06-07",
"monaco-gravel-race": "2026-04-19",
"montana-gravel-challenge": "2026-10-01",
"mount-baker-hill-climb": "2026-09-13",
"mt-evans-hill-climb": "2026-07-25",
"mt-fuji-hill-climb": "2026-06-07",
"mt-washington-hillclimb": "2026-08-15",
"muck-n-mac-fest": "2026-05-02",
"muju-gran-fondo": "2026-05-17",
"munsterland-giro": "2026-10-03",
"nanaimo-unpaved": "2025-06-15",
"natchez-trace-gran-fondo": "2026-05-30",
"ned-gravel": "2026-07-12",
"neusiedlersee-radmarathon": "2026-04-18",
"nicolet-hot-days": "2025-08-10",
"niseko-classic": "2026-06-21",
"niseko-gravel": "2025-09-14",
"noosa-gravel-enduro": "2026-06-21",
"nordsjorittet": "2026-06-13",
"north-wales-gravel-x": "2026-04-25",
"northcape-4000": "2026-07-25",
"nove-colli": "2026-05-24",
"nxt-classic": "2026-04-06",
"nyc-century": "2025-09-21",
"ocbc-cycle-singapore": "2026-05-09",
"old-fashioned-gravel": "2026-10-03",
"omg-oxford-ms-gravel": "2026-01-11",
"omloop-het-nieuwsblad-sportive": "2026-03-01",
"opelika-okey-dokey": "2026-05-09",
"oregon-coast-gravel-epic": "2027-05-01",
"oregon-gran-fondo": "2026-05-16",
"oregon-trail-gravel": "2026-07-08",
"ottawa-valley-gravel-experience": "2026-04-11",
"otztaler-radmarathon": "2026-08-30",
"ouachita-challenge": "2026-03-28",
"ozark-gravel": "2026-03-07",
"pan-celtic-ultra": "2026-07-11",
"pan-mass-challenge": "2026-08-01",
"paris-brest-paris": "2027-08-22",
"paris-mountain-gravel-grinder": "2026-06-28",
"paris-roubaix-challenge": "2026-04-11",
"paris-to-ancaster": "2026-04-26",
"parker-dam-gravel-grinder": "2026-05-09",
"peaks-and-plains": "2026-05-29",
"peaks-challenge-falls-creek": "2026-03-07",
"pekan-classics": "2026-06-28",
"pelotonia": "2026-08-01",
"perth-hills-gran-fondo": "2026-03-29",
"pickerel-buck40": "2025-06-15",
"pirinexus-360": "2026-09-18",
"pisgah-monster-cross": "2026-09-12",
"polish-gravel": "2026-08-08",
"pony-express-120": "2026-09-07",
"pony-xpress-gravel-160": "2026-05-09",
"prairie-burn-100": "2026-06-06",
"prosecco-cycling": "2026-09-27",
"quebrantahuesos": "2026-06-20",
"race-across-america": "2026-06-16",
"race-across-belgium": "2026-05-27",
"race-across-benelux": "2026-05-27",
"race-across-france": "2026-06-18",
"race-across-germany": "2026-07-02",
"race-across-italy-300": "2026-05-02",
"race-across-portugal": "2026-03-25",
"race-across-spain": "2026-09-16",
"race-around-netherlands": "2026-05-02",
"race-around-poland": "2026-06-27",
"race-around-rwanda": "2026-02-01",
"race-through-poland": "2026-05-23",
"race-to-valhalla": "2027-04-24",
"rad-am-ring": "2026-07-24",
"rad-am-ring-gravel": "2026-07-26",
"radl-grvl": "2026-01-23",
"ragbrai": "2026-07-18",
"raid-rockingham": "2026-06-07",
"rasputitsa-spring-classic": "2026-03-28",
"raul-alcala-challenge-oaxaca": "2026-04-19",
"real-west-gravel": "2026-03-15",
"rebeccas-private-idaho": "2026-09-12",
"red-granite-grinder": "2026-10-10",
"redlands-bicycle-classic": "2026-04-11",
"reliance-deep-woods": "2026-04-24",
"reliance-tennessee-gravel": "2025-09-01",
"ride-across-britain": "2026-09-05",
"ride-across-indiana": "2026-06-27",
"ride-across-wisconsin": "2026-07-11",
"ride-the-gravel-trails": "2026-04-26",
"rift-valley-odyssey": "2026-09-21",
"ring-of-clare": "2026-07-18",
"ring-of-kerry-charity-cycle": "2026-07-04",
"river-city-gravel-fondo": "2026-04-12",
"rock-cobbler": "2026-02-07",
"rose-city-rampage": "2025-03-22",
"round-denmark-bike-race": "2026-07-05",
"ruby-roubaix": "2027-06-26",
"rust-buster-gravel-fondo": "2025-04-05",
"sado-long-ride-210": "2026-05-17",
"safari-gravel-race": "2027-06-12",
"salida-76": "2026-09-19",
"salty-lizard": "2026-04-04",
"santa-fe-century-gravelon": "2027-05-15",
"sasquatch-duro": "2027-04-24",
"schleck-gran-fondo": "2026-05-30",
"scratch-ankle-gravel": "2026-03-21",
"sea-otter-ciclobrava": "2026-09-20",
"sea-otter-classic-gran-fondo": "2026-04-18",
"sea-otter-europe-gravel": "2026-09-19",
"sea-otter-gravel": "2027-04-15",
"seattle-to-portland": "2026-07-11",
"sellaronda-bike-day": "2026-06-06",
"serenissima-gravel": "2025-10-17",
"sierra-nevada-limite": "2026-05-23",
"silver-city-century": "2026-05-24",
"soldier-cutoff-hillduro": "2026-09-19",
"sovev-jerusalem": "2026-05-08",
"spinneys-dubai-92": "2026-02-15",
"spirit-world-100": "2026-11-07",
"sportful-dolomiti-race": "2026-06-14",
"spotted-horse-ultra": "2026-10-17",
"spring-thaw": "2026-04-12",
"spring-valley-100": "2026-05-16",
"sriwijaya-ranau-gran-fondo": "2025-11-15",
"standard-deluxe-dirt-road-century": "2025-11-08",
"steamboat-gravel": "2027-06-28",
"strade-bianche-gran-fondo": "2026-03-08",
"struggle-dales": "2026-05-24",
"struggle-moors": "2026-07-05",
"styrkeproven": "2026-06-20",
"sudety-tour": "2026-05-09",
"sunday-creek-classic": "2026-05-23",
"superior-morgul-road-race": "2026-05-17",
"surrey-rumble": "2026-05-17",
"suzuka-endurance-road": "2026-07-03",
"swamp-fox-gravel-fondo": "2026-03-21",
"switchgrass": "2025-04-05",
"taiwan-kom-challenge": "2026-10-23",
"takelma-gravel-grinder": "2026-06-27",
"tallinn-gran-fondo": "2026-08-15",
"tartu-rattaralli": "2026-06-07",
"texas-hell-week": "2026-03-21",
"the-accursed-race": "2026-05-12",
"the-divide": "2026-07-26",
"the-equalizer": "2026-11-07",
"the-grit-adventure": "2026-07-18",
"the-insayner": "2026-06-13",
"the-mane-event-gravel": "2026-09-19",
"the-millars-gran-fondo": "2026-03-22",
"the-rad": "2026-09-26",
"the-range": "2026-07-11",
"the-rift": "2026-07-04",
"the-traka": "2027-04-30",
"the-watermoo": "2026-08-08",
"thunder-bay-thriller": "2026-08-29",
"tjejvattern": "2026-06-06",
"tor-divide": "2026-05-17",
"torino-nice-rally": "2026-08-29",
"tortour": "2026-08-12",
"total-tomahawk-terrain": "2026-06-20",
"tour-aotearoa": "2026-02-19",
"tour-de-big-bear": "2026-08-01",
"tour-de-brisbane": "2026-04-12",
"tour-de-fukushima": "2026-06-13",
"tour-de-gap": "2026-07-25",
"tour-de-lile-de-montreal": "2026-05-31",
"tour-de-matra": "2026-05-29",
"tour-de-nebraska": "2026-06-23",
"tour-de-okinawa": "2025-11-08",
"tour-de-palm-springs": "2026-02-07",
"tour-de-pologne-amatorow": "2026-08-01",
"tour-de-romandie-cyclosportive": "2026-04-28",
"tour-de-suisse-challenge": "2026-06-11",
"tour-down-under-community-ride": "2026-01-18",
"tour-du-mont-blanc-cyclo": "2026-06-28",
"tour-durban": "2026-04-19",
"tour-of-flanders-sportive": "2026-04-04",
"tour-of-georgia-gran-fondo": "2026-04-19",
"tour-of-nilgiris": "2026-12-12",
"tour-of-pembrokeshire": "2026-05-23",
"tour-of-southland": "2026-01-18",
"tour-of-the-battenkill-road": "2026-05-09",
"tour-of-the-gila": "2026-04-29",
"tour-of-the-peak": "2026-05-17",
"tour-of-thekkady": "2026-03-14",
"trans-iowa": "2025-04-19",
"trans-pyrenees-race": "2026-09-25",
"trans-sylvania-epic": "2026-05-19",
"transatlanticway": "2026-06-18",
"transcontinental-race": "2026-07-19",
"transiberica": "2026-08-22",
"transrockies-gravel-royale": "2026-08-21",
"trek-100": "2026-06-06",
"trek-across-maine": "2026-06-19",
"triple-bypass": "2026-07-11",
"trough-creek-gravel-grinder": "2026-09-20",
"truckee-tahoe-gravel": "2026-06-27",
"turkcell-granfondo-izmir": "2026-10-04",
"turnhout-gravel": "2026-08-30",
"two-volcano-sprint": "2026-04-26",
"uci-gran-fondo-ireland": "2026-06-27",
"uci-gran-fondo-world-championships": "2026-08-26",
"uci-gravel-dustman": "2026-11-14",
"uci-gravel-worlds": "2026-10-10",
"unbound-100": "2026-05-30",
"unbound-200": "2026-05-30",
"uncle-johns-gravel-race": "2026-09-13",
"unravel-gravel-va": "2026-09-20",
"usa-cycling-gravel-nationals": "2026-09-12",
"utrecht-ultra": "2026-05-23",
"uwharrie-forest-gravel-grinder": "2027-02-21",
"valley-granfondo": "2026-06-07",
"vapor-trail-125": "2026-09-12",
"vatternrundan": "2026-06-12",
"velo-vietnam-northern-frontier": "2026-10-02",
"velomediane-criquielion": "2026-08-22",
"velothon-berlin": "2024-07-28",
"veneto-gravel": "2025-11-20",
"vermont-overland": "2026-08-15",
"viana-granfondo": "2026-03-15",
"vuelta-altas-cumbres": "2027-03-21",
"wadi-dayqah-challenge": "2026-01-24",
"wasatch-all-road": "2026-08-29",
"waucheesi-bike-race": "2027-03-28",
"waukon-100": "2026-06-20",
"west-coast-gravel": "2026-05-03",
"whiskey-off-road": "2026-04-24",
"whistler-granfondo": "2026-09-12",
"white-horse-challenge": "2026-04-19",
"white-rose-classic": "2026-05-31",
"wicklow-200": "2026-06-07",
"wild-gravel": "2026-10-24",
"wild-horse-gravel": "2027-05-15",
"wish-one-millau": "2027-06-13",
"wollombi-gravel-fest": "2025-12-21",
"worthersee-gravel-race": "2027-04-18",
"wyo-131": "2026-09-12",
"yorkshire-coast-dirt-dash": "2026-06-14"
}